local_feature_tutorial/__init__.py
local_feature_tutorial/_nbdev.py
local_feature_tutorial/datasets.py
local_feature_tutorial/io.py
local_feature_tutorial/retrieval.py
local_feature_tutorial/visualization.py
local_feature_tutorial/wbs.py
local_feature_tutorial-0.0.3.dist-info/LICENSE
local_feature_tutorial-0.0.3.dist-info/METADATA
local_feature_tutorial-0.0.3.dist-info/WHEEL
local_feature_tutorial-0.0.3.dist-info/entry_points.txt
local_feature_tutorial-0.0.3.dist-info/top_level.txt
local_feature_tutorial-0.0.3.dist-info/RECORD
