Metadata-Version: 2.1
Name: local-feature-tutorial
Version: 0.0.3
Summary: DIY image retrieval with spatial verification
Home-page: https://github.com/ducha-aiki/local_feature_tutorial/tree/master/
Author: Dmytro Mishkin
Author-email: ducha.aiki@gmail.com
License: Apache Software License 2.0
Keywords: wide baseline stereo,SIFT,HardNet,image retrieval
Platform: UNKNOWN
Classifier: Development Status :: 3 - Alpha
Classifier: Intended Audience :: Developers
Classifier: License :: OSI Approved :: Apache Software License
Classifier: Natural Language :: English
Classifier: Programming Language :: Python :: 3.6
Classifier: Programming Language :: Python :: 3.7
Classifier: Programming Language :: Python :: 3.8
Requires-Python: >=3.6
Requires-Dist: google-colab
Requires-Dist: Pillow
Requires-Dist: opencv-python (>=4.4.0)
Requires-Dist: torch
Requires-Dist: matplotlib
Requires-Dist: wget
Requires-Dist: kornia (>=0.4.1)
Requires-Dist: torchvision
Requires-Dist: fastcore
Requires-Dist: fastprogress (>=0.2.4)
Requires-Dist: numpy
Requires-Dist: pydegensac
